[ {
  "orderNo" : "00FEBC3F",
  "orderOutcome" : "Delivered",
  "costInPence" : 2400
}, {
  "orderNo" : "3F91242C",
  "orderOutcome" : "Delivered",
  "costInPence" : 2400
}, {
  "orderNo" : "794D2CFB",
  "orderOutcome" : "Delivered",
  "costInPence" : 2400
}, {
  "orderNo" : "7B1FBA2A",
  "orderOutcome" : "Delivered",
  "costInPence" : 2400
}, {
  "orderNo" : "792BBFEF",
  "orderOutcome" : "Delivered",
  "costInPence" : 2400
}, {
  "orderNo" : "0C74DCD0",
  "orderOutcome" : "Delivered",
  "costInPence" : 2400
}, {
  "orderNo" : "50D6D80B",
  "orderOutcome" : "Delivered",
  "costInPence" : 2400
}, {
  "orderNo" : "348EF826",
  "orderOutcome" : "Delivered",
  "costInPence" : 2400
}, {
  "orderNo" : "7270B6A5",
  "orderOutcome" : "Delivered",
  "costInPence" : 2400
}, {
  "orderNo" : "7A38A9EB",
  "orderOutcome" : "Delivered",
  "costInPence" : 2400
}, {
  "orderNo" : "05AADF43",
  "orderOutcome" : "Delivered",
  "costInPence" : 2500
}, {
  "orderNo" : "0B42201B",
  "orderOutcome" : "Delivered",
  "costInPence" : 2500
}, {
  "orderNo" : "3BAAC149",
  "orderOutcome" : "Delivered",
  "costInPence" : 2500
}, {
  "orderNo" : "0EF50421",
  "orderOutcome" : "Delivered",
  "costInPence" : 2500
}, {
  "orderNo" : "2EF40E5C",
  "orderOutcome" : "Delivered",
  "costInPence" : 2500
}, {
  "orderNo" : "7902B0FF",
  "orderOutcome" : "Delivered",
  "costInPence" : 2500
}, {
  "orderNo" : "2442691B",
  "orderOutcome" : "Delivered",
  "costInPence" : 2500
}, {
  "orderNo" : "4E058DBD",
  "orderOutcome" : "Delivered",
  "costInPence" : 2500
}, {
  "orderNo" : "21E5FFD6",
  "orderOutcome" : "Delivered",
  "costInPence" : 2500
}, {
  "orderNo" : "4C478D64",
  "orderOutcome" : "Delivered",
  "costInPence" : 2500
}, {
  "orderNo" : "05E5B502",
  "orderOutcome" : "Delivered",
  "costInPence" : 2400
}, {
  "orderNo" : "1A6F51AF",
  "orderOutcome" : "Delivered",
  "costInPence" : 2400
}, {
  "orderNo" : "56140453",
  "orderOutcome" : "Delivered",
  "costInPence" : 2400
}, {
  "orderNo" : "0D2A31C9",
  "orderOutcome" : "Delivered",
  "costInPence" : 2400
}, {
  "orderNo" : "71079027",
  "orderOutcome" : "Delivered",
  "costInPence" : 2400
}, {
  "orderNo" : "3F6FF11A",
  "orderOutcome" : "Delivered",
  "costInPence" : 2400
}, {
  "orderNo" : "2AE9B98F",
  "orderOutcome" : "Delivered",
  "costInPence" : 2400
}, {
  "orderNo" : "5956C28B",
  "orderOutcome" : "Delivered",
  "costInPence" : 2400
}, {
  "orderNo" : "763B0C2F",
  "orderOutcome" : "Delivered",
  "costInPence" : 2400
}, {
  "orderNo" : "7E63701D",
  "orderOutcome" : "ValidButNotDelivered",
  "costInPence" : 2400
}, {
  "orderNo" : "27478F9F",
  "orderOutcome" : "ValidButNotDelivered",
  "costInPence" : 2600
}, {
  "orderNo" : "177B2D8B",
  "orderOutcome" : "ValidButNotDelivered",
  "costInPence" : 2600
}, {
  "orderNo" : "560656C3",
  "orderOutcome" : "ValidButNotDelivered",
  "costInPence" : 2600
}, {
  "orderNo" : "00D358B5",
  "orderOutcome" : "ValidButNotDelivered",
  "costInPence" : 2600
}, {
  "orderNo" : "6BFA2BB5",
  "orderOutcome" : "ValidButNotDelivered",
  "costInPence" : 2600
}, {
  "orderNo" : "556CF726",
  "orderOutcome" : "ValidButNotDelivered",
  "costInPence" : 2600
}, {
  "orderNo" : "057DC394",
  "orderOutcome" : "ValidButNotDelivered",
  "costInPence" : 2600
}, {
  "orderNo" : "305FE67F",
  "orderOutcome" : "ValidButNotDelivered",
  "costInPence" : 2600
}, {
  "orderNo" : "316EA080",
  "orderOutcome" : "ValidButNotDelivered",
  "costInPence" : 2600
}, {
  "orderNo" : "6E8479C0",
  "orderOutcome" : "ValidButNotDelivered",
  "costInPence" : 2600
}, {
  "orderNo" : "2651B056",
  "orderOutcome" : "InvalidCardNumber",
  "costInPence" : 2500
}, {
  "orderNo" : "3D7726D7",
  "orderOutcome" : "InvalidExpiryDate",
  "costInPence" : 2600
}, {
  "orderNo" : "77293EB6",
  "orderOutcome" : "InvalidCvv",
  "costInPence" : 2400
}, {
  "orderNo" : "0556E90B",
  "orderOutcome" : "InvalidTotal",
  "costInPence" : 2528
}, {
  "orderNo" : "43BDEA07",
  "orderOutcome" : "InvalidPizzaNotDefined",
  "costInPence" : 2500
}, {
  "orderNo" : "23059899",
  "orderOutcome" : "InvalidPizzaCount",
  "costInPence" : 12600
}, {
  "orderNo" : "2A57DB84",
  "orderOutcome" : "InvalidPizzaCombinationMultipleSuppliers",
  "costInPence" : 3400
} ]